{"Cookie":"h1_device_id=TO_ADD; __Host-session=TO_ADD",
"User-Agent": "Mozilla/5.0 (X11; Ubuntu; Linux x86_64; rv:90.0) Gecko/20100101 Firefox/90.0",
"Accept": "*/*",
"Accept-Language": "en-US,en;q=0.5",
"Accept-Encoding": "gzip, deflate",
"Referer": "https://hackerone.com/spotify?type=team",
"Content-Type": "application/json",
"X-Auth-Token": "----",
"Origin": "https://hackerone.com",
"Content-Length": "4520",
"Sec-Fetch-Dest": "empty",
"Sec-Fetch-Mode": "cors",
"Sec-Fetch-Site": "same-origin",
"Te": "trailers"}